sap_odata/__init__.py
sap_odata/client.py
sap_odata/exceptions.py
sap_odata/py.typed
sap_odata_python-1.2.0.dist-info/licenses/LICENSE
sap_odata_python-1.2.0.dist-info/METADATA
sap_odata_python-1.2.0.dist-info/WHEEL
sap_odata_python-1.2.0.dist-info/top_level.txt
sap_odata_python-1.2.0.dist-info/RECORD
