Metadata-Version: 2.4
Name: sap-odata-python
Version: 1.2.0
Summary: AI/LLM-friendly Python client for SAP OData V2 and V4 APIs - single generic function for all operations
Author: Vaibhav Goel
Maintainer: Vaibhav Goel
License-Expression: Apache-2.0
Project-URL: Homepage, https://github.com/vaibhavgoel-github-1986/sap-odata-python
Project-URL: Repository, https://github.com/vaibhavgoel-github-1986/sap-odata-python
Project-URL: Documentation, https://github.com/vaibhavgoel-github-1986/sap-odata-python#readme
Project-URL: Issues, https://github.com/vaibhavgoel-github-1986/sap-odata-python/issues
Project-URL: Changelog, https://github.com/vaibhavgoel-github-1986/sap-odata-python/releases
Keywords: odata,odata-v2,odata-v4,sap,sap-api,sap-odata,rest-api,rest-client,api-client,ai-friendly,llm,mcp,model-context-protocol
Classifier: Development Status :: 5 - Production/Stable
Classifier: Intended Audience :: Developers
Classifier: Intended Audience :: Information Technology
Classifier: Intended Audience :: System Administrators
Classifier: Operating System :: OS Independent
Classifier: Programming Language :: Python :: 3
Classifier: Programming Language :: Python :: 3.8
Classifier: Programming Language :: Python :: 3.9
Classifier: Programming Language :: Python :: 3.10
Classifier: Programming Language :: Python :: 3.11
Classifier: Programming Language :: Python :: 3.12
Classifier: Topic :: Software Development :: Libraries :: Python Modules
Classifier: Topic :: Internet :: WWW/HTTP
Classifier: Topic :: Internet :: WWW/HTTP :: Dynamic Content
Classifier: Topic :: Office/Business :: Financial :: Accounting
Classifier: Topic :: Database :: Front-Ends
Classifier: Typing :: Typed
Requires-Python: >=3.8
License-File: LICENSE
Requires-Dist: requests>=2.25.0
Provides-Extra: dev
Requires-Dist: pytest>=7.0.0; extra == "dev"
Requires-Dist: pytest-cov>=4.0.0; extra == "dev"
Dynamic: license-file
